sphinxcontrib_nwdiag-2.0.0-py3.8-nspkg.pth
sphinxcontrib/nwdiag.py
sphinxcontrib/packetdiag.py
sphinxcontrib/rackdiag.py
sphinxcontrib_nwdiag-2.0.0.dist-info/AUTHORS
sphinxcontrib_nwdiag-2.0.0.dist-info/LICENSE
sphinxcontrib_nwdiag-2.0.0.dist-info/METADATA
sphinxcontrib_nwdiag-2.0.0.dist-info/WHEEL
sphinxcontrib_nwdiag-2.0.0.dist-info/namespace_packages.txt
sphinxcontrib_nwdiag-2.0.0.dist-info/top_level.txt
sphinxcontrib_nwdiag-2.0.0.dist-info/RECORD
